heimdall_cli/__init__.py
heimdall_cli/encryption/__init__.py
heimdall_cli/encryption/encryption.py
heimdall_cli/encryption/s_box.py
heimdall_cli/helpers/__init__.py
heimdall_cli/helpers/api_service.py
heimdall_cli/helpers/config_manager.py
heimdall_cli/helpers/utils.py
heimdall_cli/main.py
heimdall_cli/subcommands/__init__.py
heimdall_cli/subcommands/auth.py
heimdall_cli/subcommands/files.py
heimdall_cli-0.1.5.dist-info/METADATA
heimdall_cli-0.1.5.dist-info/WHEEL
heimdall_cli-0.1.5.dist-info/entry_points.txt
heimdall_cli-0.1.5.dist-info/RECORD
