Metadata-Version: 2.3
Name: heimdall-cli
Version: 0.1.5
Summary: Command-line utility for secure and efficient file encryption and storage.
License: MIT
Author: amin masoudi
Author-email: aminmasoudi2003@gmail.com
Requires-Python: >=3.10
Classifier: License :: OSI Approved :: MIT License
Classifier: Programming Language :: Python :: 3
Classifier: Programming Language :: Python :: 3.10
Classifier: Programming Language :: Python :: 3.11
Classifier: Programming Language :: Python :: 3.12
Classifier: Programming Language :: Python :: 3.13
Requires-Dist: click (>=8.2.1,<9.0.0)
Requires-Dist: httpx (>=0.28.1,<0.29.0)
